cdx_toolkit/__init__.py
cdx_toolkit/commoncrawl.py
cdx_toolkit/compat.py
cdx_toolkit/myrequests.py
cdx_toolkit/timestamp.py
cdx_toolkit/timeutils.py
cdx_toolkit/timeutils_new.py
cdx_toolkit/warc.py
cdx_toolkit-0.9.20.data/scripts/cdx_iter
cdx_toolkit-0.9.20.data/scripts/cdx_size
cdx_toolkit-0.9.20.dist-info/LICENSE
cdx_toolkit-0.9.20.dist-info/METADATA
cdx_toolkit-0.9.20.dist-info/WHEEL
cdx_toolkit-0.9.20.dist-info/top_level.txt
cdx_toolkit-0.9.20.dist-info/RECORD
