Metadata-Version: 2.1
Name: cdx-toolkit
Version: 0.9.20
Summary: A toolkit for working with CDX indices
Home-page: https://github.com/cocrawler/cdx_toolkit
Author: Greg Lindahl and others
Author-email: lindahl@pbm.com
License: Apache 2.0
Platform: UNKNOWN
Classifier: Development Status :: 4 - Beta
Classifier: Environment :: Console
Classifier: Intended Audience :: Information Technology
Classifier: Intended Audience :: Developers
Classifier: Natural Language :: English
Classifier: License :: OSI Approved :: Apache Software License
Classifier: Programming Language :: Python
Classifier: Programming Language :: Python :: 3.4
Classifier: Programming Language :: Python :: 3.5
Classifier: Programming Language :: Python :: 3.6
Classifier: Programming Language :: Python :: 3.7
Classifier: Programming Language :: Python :: 3 :: Only
Requires-Dist: requests
Requires-Dist: warcio
